CHANGES.txt
CONTRIBUTORS.txt
MANIFEST.in
README.txt
plumi.skin-configure.zcml
setup.cfg
setup.py
docs/INSTALL.txt
docs/LICENSE.GPL
docs/LICENSE.txt
plumi/__init__.py
plumi.skin.egg-info/PKG-INFO
plumi.skin.egg-info/SOURCES.txt
plumi.skin.egg-info/dependency_links.txt
plumi.skin.egg-info/entry_points.txt
plumi.skin.egg-info/namespace_packages.txt
plumi.skin.egg-info/not-zip-safe
plumi.skin.egg-info/paster_plugins.txt
plumi.skin.egg-info/requires.txt
plumi.skin.egg-info/top_level.txt
plumi/skin/__init__.py
plumi/skin/adapter.py
plumi/skin/configure.zcml
plumi/skin/overrides.zcml
plumi/skin/setuphandlers.py
plumi/skin/tests.py
plumi/skin/userdataschema.py
plumi/skin/browser/.views.py.swp
plumi/skin/browser/__init__.py
plumi/skin/browser/author.py
plumi/skin/browser/authorlisting.py
plumi/skin/browser/configure.zcml
plumi/skin/browser/interfaces.py
plumi/skin/browser/views.py
plumi/skin/browser/views.py.1
plumi/skin/browser/portlets/__init__.py
plumi/skin/browser/portlets/aboutportlet.pt
plumi/skin/browser/portlets/aboutportlet.py
plumi/skin/browser/portlets/browseportlet.pt
plumi/skin/browser/portlets/browseportlet.py
plumi/skin/browser/portlets/contentportlet.pt
plumi/skin/browser/portlets/contentportlet.py
plumi/skin/browser/portlets/featuredleft.pt
plumi/skin/browser/portlets/featuredleft.py
plumi/skin/browser/portlets/featuredright.pt
plumi/skin/browser/portlets/featuredright.py
plumi/skin/browser/portlets/featuredtop.pt
plumi/skin/browser/portlets/featuredtop.py
plumi/skin/browser/portlets/newsandevents.pt
plumi/skin/browser/portlets/newsandevents.py
plumi/skin/browser/portlets/publishportlet.pt
plumi/skin/browser/portlets/publishportlet.py
plumi/skin/browser/templates/authorlist.pt
plumi/skin/browser/templates/search.pt
plumi/skin/browser/templates/taxonomy.pt
plumi/skin/browser/templates/updated_search.pt
plumi/skin/locales/en/LC_MESSAGES/plonelocales.mo
plumi/skin/locales/en/LC_MESSAGES/plonelocales.po
plumi/skin/profiles/default/browserlayer.xml
plumi/skin/profiles/default/componentregistry.xml
plumi/skin/profiles/default/cssregistry.xml
plumi/skin/profiles/default/import_steps.xml
plumi/skin/profiles/default/jsregistry.xml
plumi/skin/profiles/default/memberdata_properties.xml
plumi/skin/profiles/default/metadata.xml
plumi/skin/profiles/default/portlets.xml
