Metadata-Version: 1.0
Name: plumi.skin
Version: 4.5
Summary: Plumi Skin
Home-page: http://plumi.org/
Author: Andy Nicholson
Author-email: andy@infiniterecursion.com.au
License: GPL
Download-URL: https://github.com/plumi/plumi.skin
Keywords: plone plumi skin
Platform: UNKNOWN
Classifier: Framework :: Plone
Classifier: Programming Language :: Python
Classifier: Topic :: Software Development :: Libraries :: Python Modules
